{"name":"Aurora","slug":"blog-author","avatar":"https://img-blog.csdnimg.cn/20210313122054101.png","link":"/","description":"","socials":{"github":"","twitter":"","stackoverflow":"","wechat":"","qq":"","weibo":"","zhihu":"","csdn":"","juejin":"","customs":{}},"post_list":[{"title":"paper","uid":"46eb565a65fe49e5580671c295cf9563","slug":"paper","date":"2021-12-13T14:03:20.000Z","updated":"2021-12-13T14:03:20.088Z","comments":true,"path":"api/articles/paper.json","keywords":null,"cover":null,"text":"","link":"","photos":[],"count_time":{"symbolsCount":0,"symbolsTime":"1 mins."},"categories":[],"tags":[],"author":{"name":"Aurora","slug":"blog-author","avatar":"https://img-blog.csdnimg.cn/20210313122054101.png","link":"/","description":"","socials":{"github":"","twitter":"","stackoverflow":"","wechat":"","qq":"","weibo":"","zhihu":"","csdn":"","juejin":"","customs":{}}}},{"title":"Hello World","uid":"b9663f58f18133b35bfe243f3e916a80","slug":"hello-world","date":"2021-12-12T02:51:38.396Z","updated":"2021-12-12T02:51:38.397Z","comments":true,"path":"api/articles/hello-world.json","keywords":null,"cover":null,"text":"Welcome to Hexo! This is your very first post. Check documentation for more info. If you get any problems when using Hexo, you can find the ...","link":"","photos":[],"count_time":{"symbolsCount":430,"symbolsTime":"1 mins."},"categories":[],"tags":[],"author":{"name":"Aurora","slug":"blog-author","avatar":"https://img-blog.csdnimg.cn/20210313122054101.png","link":"/","description":"","socials":{"github":"","twitter":"","stackoverflow":"","wechat":"","qq":"","weibo":"","zhihu":"","csdn":"","juejin":"","customs":{}}}}],"categories":0,"tags":0,"word_count":430,"post_count":2}